efnlp/__init__.py
efnlp/__main__.py
efnlp/beam.py
efnlp/encoder.py
efnlp/language.py
efnlp/sampler.py
efnlp/suffixtree.py
efnlp/types.py
efnlp/util.py
efnlp-0.1.14.dist-info/WHEEL
efnlp-0.1.14.dist-info/METADATA
efnlp-0.1.14.dist-info/RECORD
