Metadata-Version: 2.1
Name: efnlp
Version: 0.1.14
Summary: Empirical Frequency Natural Language Processing
Author: W. Ross Morrow
Author-email: morrowwr@gmail.com
Requires-Python: >=3.9,<4.0
Classifier: Programming Language :: Python :: 3
Classifier: Programming Language :: Python :: 3.10
Classifier: Programming Language :: Python :: 3.9
Requires-Dist: protobuf (>=3.19,<4.0)
